tool_sync/__init__.py
tool_sync/azure_devops_client.py
tool_sync/config.py
tool_sync/local_file_system.py
tool_sync/main.py
tool_sync/mcp_server.py
tool_sync/models.py
tool_sync/sync_engine.py
tool_sync/analysis/__init__.py
tool_sync/analysis/indexing.py
tool_sync/analysis/query.py
tool_sync-0.6.5.dist-info/licenses/LICENSE
tool_sync-0.6.5.dist-info/METADATA
tool_sync-0.6.5.dist-info/WHEEL
tool_sync-0.6.5.dist-info/entry_points.txt
tool_sync-0.6.5.dist-info/top_level.txt
tool_sync-0.6.5.dist-info/RECORD
