Metadata-Version: 2.4
Name: tool_sync
Version: 0.6.5
Summary: A bidirectional synchronization tool for Azure DevOps work items.
Home-page: https://github.com/fabioribeiroquispe/tool_sync
Author: Fábio Ribeiro dos Santos Quispe
Author-email: fabiorisantos1981@gmail.com
License: MIT
Keywords: azure devops,sync,synchronization,work items
Classifier: Development Status :: 3 - Alpha
Classifier: Intended Audience :: Developers
Classifier: Programming Language :: Python :: 3
Classifier: Programming Language :: Python :: 3.10
License-File: LICENSE
Requires-Dist: PyYAML==6.0.1
Requires-Dist: python-dateutil==2.9.0
Requires-Dist: requests==2.31.0
Requires-Dist: Jinja2==3.1.2
Provides-Extra: analysis
Requires-Dist: mcp[cli]==1.13.1; extra == "analysis"
Requires-Dist: beautifulsoup4==4.12.3; extra == "analysis"
Requires-Dist: qdrant-client==1.9.0; extra == "analysis"
Requires-Dist: fastembed==0.2.7; extra == "analysis"
Dynamic: author
Dynamic: author-email
Dynamic: classifier
Dynamic: description
Dynamic: description-content-type
Dynamic: home-page
Dynamic: keywords
Dynamic: license
Dynamic: license-file
Dynamic: summary
